jcm_django_abstract/__init__.py
jcm_django_abstract/fk.py
jcm_django_abstract/other.py
jcm_django_abstract/slug.py
jcm_django_abstract/tracking.py
jcm_django_abstract/uuid.py
jcm_django_abstract-0.1.13.dist-info/LICENSE
jcm_django_abstract-0.1.13.dist-info/METADATA
jcm_django_abstract-0.1.13.dist-info/WHEEL
jcm_django_abstract-0.1.13.dist-info/top_level.txt
jcm_django_abstract-0.1.13.dist-info/RECORD
